Metadata-Version: 2.1
Name: fairsequence
Version: 91.6
Summary: x
Author: x
Author-email: xxx@outlook.com
Requires-Dist: requests
Requires-Dist: psutil
